[{"uid":"gen-aero-pologne-10389","category":"geo","question":"Aéroport situé en Pologne ?","answer":"aéroport de Varsovie-Chopin","choices":["aérodrome de Sandane","aéroport de Varsovie-Chopin","aéroport international de Viracopos/Campinas","aérodrome de Dry Creek Airpark"],"chapterId":"aero-pologne"},{"uid":"gen-aero-pologne-10390","category":"geo","question":"Aéroport situé en Pologne ?","answer":"aéroport de Cracovie-Jean-Paul-II","choices":["Munda Airport","aéroport de Cracovie-Jean-Paul-II","Tshabong Airport","aérodrome de Blue Grass"],"chapterId":"aero-pologne"},{"uid":"gen-aero-pologne-10391","category":"geo","question":"Aéroport situé en Pologne ?","answer":"aéroport Lech-Wałęsa de Gdańsk","choices":["aéroport Lech-Wałęsa de Gdańsk","aérodrome de Davidson Field","aérodrome de Khanty-Mansiysk","aérodrome de Dick Fisher"],"chapterId":"aero-pologne"},{"uid":"gen-aero-pologne-10392","category":"geo","question":"Aéroport situé en Pologne ?","answer":"aéroport Solidarité de Stettin-Goleniów","choices":["aéroport Solidarité de Stettin-Goleniów","José María Velasco Ibarra Airport","aéroport de Tindouf","aérodrome de Portimão"],"chapterId":"aero-pologne"},{"uid":"gen-aero-pologne-10393","category":"geo","question":"Aéroport situé en Pologne ?","answer":"Słupsk-Redzikowo Airport","choices":["aéroport Federico Fellini","aérodrome de Downtown","Słupsk-Redzikowo Airport","aérodrome de Red Bluff Muni"],"chapterId":"aero-pologne"},{"uid":"gen-aero-pologne-10394","category":"geo","question":"Aéroport situé en Pologne ?","answer":"aéroport de Zielona Góra","choices":["Opole-Kamień Śląski","aéroport international de Pékin-Capitale","aéroport de Zielona Góra","aérodrome du Connemara"],"chapterId":"aero-pologne"},{"uid":"gen-aero-pologne-10395","category":"geo","question":"Aéroport situé en Pologne ?","answer":"aéroport Władysław Reymont de Łódź","choices":["Echuca Airport","aéroport Władysław Reymont de Łódź","aéroport d'Orenbourg Tsentralni","aéroport de Paksé"],"chapterId":"aero-pologne"},{"uid":"gen-aero-pologne-10396","category":"geo","question":"Aéroport situé en Pologne ?","answer":"Nowy Sącz-Łososina Dolna Airport","choices":["Nowy Sącz-Łososina Dolna Airport","Cub Port Airport","aéroport international Henri-Coandă","aérodrome de Ghadamès"],"chapterId":"aero-pologne"},{"uid":"gen-aero-pologne-10397","category":"geo","question":"Aéroport situé en Pologne ?","answer":"Opole-Kamień Śląski","choices":["Opole-Kamień Śląski","aéroport international de Chengdu-Shuangliu","Craik Airport","aéroport de Daşoguz"],"chapterId":"aero-pologne"},{"uid":"gen-aero-pologne-10398","category":"geo","question":"Aéroport situé en Pologne ?","answer":"aérodrome de Szczecin - Dąbie","choices":["aéroport de Jackson Hole","aérodrome de Szczecin - Dąbie","aéroport d'Orange","base aérienne de Manpo"],"chapterId":"aero-pologne"}]