[{"uid":"gen-chant-saint-empire-romain-germa-14386","category":"arts","question":"Chanteur/chanteuse Saint-Empire romain germanique ?","answer":"Wolfram von Eschenbach","choices":["John Denver","Sophie Monk","Wolfram von Eschenbach","Ayaka"],"chapterId":"chant-saint-empire-romain-germa"},{"uid":"gen-chant-saint-empire-romain-germa-14387","category":"arts","question":"Chanteur/chanteuse Saint-Empire romain germanique ?","answer":"Hans Sachs","choices":["Hans Sachs","Miriam Makeba","Josef Witt","Ricky Nelson"],"chapterId":"chant-saint-empire-romain-germa"},{"uid":"gen-chant-saint-empire-romain-germa-14388","category":"arts","question":"Chanteur/chanteuse Saint-Empire romain germanique ?","answer":"Maria Barbara Bach","choices":["Maria Barbara Bach","Thomas Godoj","India.Arie","Charlotte Rae"],"chapterId":"chant-saint-empire-romain-germa"},{"uid":"gen-chant-saint-empire-romain-germa-14389","category":"arts","question":"Chanteur/chanteuse Saint-Empire romain germanique ?","answer":"Heinrich Frauenlob","choices":["Victoria Silvstedt","Heinrich Frauenlob","Valérie Sajdik","Tiffany Thornton"],"chapterId":"chant-saint-empire-romain-germa"},{"uid":"gen-chant-saint-empire-romain-germa-14390","category":"arts","question":"Chanteur/chanteuse Saint-Empire romain germanique ?","answer":"Walther von der Vogelweide","choices":["Tony Marshall","Walther von der Vogelweide","Verbal","Sylvia Syms"],"chapterId":"chant-saint-empire-romain-germa"},{"uid":"gen-chant-saint-empire-romain-germa-14391","category":"arts","question":"Chanteur/chanteuse Saint-Empire romain germanique ?","answer":"Johann Adolph Hasse","choices":["Massari","Greg Lake","Johann Adolph Hasse","Grethe Weiser"],"chapterId":"chant-saint-empire-romain-germa"},{"uid":"gen-chant-saint-empire-romain-germa-14392","category":"arts","question":"Chanteur/chanteuse Saint-Empire romain germanique ?","answer":"Johann Beer","choices":["Gackt Camui","Mia Martini","Crooked I","Johann Beer"],"chapterId":"chant-saint-empire-romain-germa"},{"uid":"gen-chant-saint-empire-romain-germa-14393","category":"arts","question":"Chanteur/chanteuse Saint-Empire romain germanique ?","answer":"François-Xavier Richter","choices":["Dorothy Dandridge","Emily Saliers","Michael Jones","François-Xavier Richter"],"chapterId":"chant-saint-empire-romain-germa"},{"uid":"gen-chant-saint-empire-romain-germa-14394","category":"arts","question":"Chanteur/chanteuse Saint-Empire romain germanique ?","answer":"Emanuel Schikaneder","choices":["Hilde Hildebrand","Raffaella Carrà","Majka Jeżowska","Emanuel Schikaneder"],"chapterId":"chant-saint-empire-romain-germa"},{"uid":"gen-chant-saint-empire-romain-germa-14395","category":"arts","question":"Chanteur/chanteuse Saint-Empire romain germanique ?","answer":"Jacobus Gallus","choices":["Joana","Chrisette Michele","Joachim Witt","Jacobus Gallus"],"chapterId":"chant-saint-empire-romain-germa"}]