[{"uid":"gen-chien-portugal-8360","category":"divers","question":"Race de chien originaire de Portugal ?","answer":"chien d'eau portugais","choices":["Petit Gascon Saintongeois","chien d'eau portugais","Kishu","Molossoïde"],"chapterId":"chien-portugal"},{"uid":"gen-chien-portugal-8361","category":"divers","question":"Race de chien originaire de Portugal ?","answer":"Chien de la Serra da Estrela","choices":["Chien de la Serra da Estrela","Chien courant de la vallée de la Save","Berner Laufhund","springer anglais"],"chapterId":"chien-portugal"},{"uid":"gen-chien-portugal-8362","category":"divers","question":"Race de chien originaire de Portugal ?","answer":"chien de Castro Laboreiro","choices":["chien de Castro Laboreiro","Hokkaïdo","Pastor Americano","Silken Windsprite"],"chapterId":"chien-portugal"},{"uid":"gen-chien-portugal-8363","category":"divers","question":"Race de chien originaire de Portugal ?","answer":"chien d'arrêt portugais","choices":["chien d'arrêt portugais","Berger croate","Welsh Corgi Pembroke","Berger belge Laekenois"],"chapterId":"chien-portugal"},{"uid":"gen-chien-portugal-8364","category":"divers","question":"Race de chien originaire de Portugal ?","answer":"fila de São Miguel","choices":["Terrier japonais","Seppala Siberian Sleddog","fila de São Miguel","Lévrier irlandais"],"chapterId":"chien-portugal"},{"uid":"gen-chien-portugal-8365","category":"divers","question":"Race de chien originaire de Portugal ?","answer":"berger de la Serra de Aires","choices":["Lévrier Tazi","Treeing Walker Coonhound","berger de la Serra de Aires","gegar colombien"],"chapterId":"chien-portugal"},{"uid":"gen-chien-portugal-8366","category":"divers","question":"Race de chien originaire de Portugal ?","answer":"chien de garenne portugais","choices":["chien de garenne portugais","Biewer Yorkshire","Griffon Fauve de Bretagne","Barzoï"],"chapterId":"chien-portugal"},{"uid":"gen-chien-portugal-8367","category":"divers","question":"Race de chien originaire de Portugal ?","answer":"rafeiro de l'Alentejo","choices":["rafeiro de l'Alentejo","Sabueso Español","Charnaigre","Chien Français blanc et noir"],"chapterId":"chien-portugal"},{"uid":"gen-chien-portugal-8368","category":"divers","question":"Race de chien originaire de Portugal ?","answer":"bouvier portugais","choices":["bouvier portugais","Colley (race de chien)","Q4353767","Épagneul bleu de Picardie"],"chapterId":"chien-portugal"},{"uid":"gen-chien-portugal-8369","category":"divers","question":"Race de chien originaire de Portugal ?","answer":"Cão de gado transmontano","choices":["Bichon bolonais","Cão de gado transmontano","bouledogue français","Braque français (type Gascogne)"],"chapterId":"chien-portugal"}]