[{"uid":"gen-ecriv-royaume-uni-4264","category":"arts","question":"Écrivain Royaume-Uni né en 1911 ?","answer":"Mervyn Peake","choices":["Karl Richard Lepsius","Wolfgang Borchert","Wilhelm Heinrich Riehl","Mervyn Peake"],"chapterId":"ecriv-royaume-uni"},{"uid":"gen-ecriv-royaume-uni-4265","category":"arts","question":"Écrivain Royaume-Uni né en 1882 ?","answer":"James Joyce","choices":["Jean-Paul Sartre","James Joyce","Brigitte Fontaine","Friedrich Hölderlin"],"chapterId":"ecriv-royaume-uni"},{"uid":"gen-ecriv-royaume-uni-4266","category":"arts","question":"Écrivain Royaume-Uni né en 1899 ?","answer":"Alfred Hitchcock","choices":["Bert Hellinger","Alfred Hitchcock","Peter Rosei","Gian Luigi Bonelli"],"chapterId":"ecriv-royaume-uni"},{"uid":"gen-ecriv-royaume-uni-4267","category":"arts","question":"Écrivain Royaume-Uni né en 1945 ?","answer":"Richard Holmes","choices":["Sándor Márai","Richard Holmes","Lorenz Friedrich Mechlenburg","Xanana Gusmão"],"chapterId":"ecriv-royaume-uni"},{"uid":"gen-ecriv-royaume-uni-4268","category":"arts","question":"Écrivain Royaume-Uni né en 1952 ?","answer":"Douglas Adams","choices":["Douglas Adams","Louis de Funès","Emil Kuh","August Friedrich Pauly"],"chapterId":"ecriv-royaume-uni"},{"uid":"gen-ecriv-royaume-uni-4269","category":"arts","question":"Écrivain Royaume-Uni né en 1889 ?","answer":"Charlie Chaplin","choices":["Ulrich Becker","Abraham von Franckenberg","Charlie Chaplin","Charlotte Buff"],"chapterId":"ecriv-royaume-uni"},{"uid":"gen-ecriv-royaume-uni-4270","category":"arts","question":"Écrivain Royaume-Uni né en 1892 ?","answer":"J. R. R. Tolkien","choices":["Milutin Milanković","Robert Hermann Schomburgk","J. R. R. Tolkien","Josef Stefan"],"chapterId":"ecriv-royaume-uni"},{"uid":"gen-ecriv-royaume-uni-4271","category":"arts","question":"Écrivain Royaume-Uni né en 1940 ?","answer":"John Lennon","choices":["Sabine Gruber","John Lennon","Wilhelm Arent","Karl-Hermann Flach"],"chapterId":"ecriv-royaume-uni"},{"uid":"gen-ecriv-royaume-uni-4272","category":"arts","question":"Écrivain Royaume-Uni né en 1850 ?","answer":"Robert Louis Stevenson","choices":["Friedrich Wilhelm Gotter","Robert Louis Stevenson","Luchino Visconti","Irmtraud Morgner"],"chapterId":"ecriv-royaume-uni"},{"uid":"gen-ecriv-royaume-uni-4273","category":"arts","question":"Écrivain Royaume-Uni né en 1903 ?","answer":"George Orwell","choices":["George Orwell","Hardy Krüger","Günther Anders","Ernst Neubach"],"chapterId":"ecriv-royaume-uni"}]