[{"uid":"gen-f1-belgique-17766","category":"sports","question":"Pilote F1 Belgique ?","answer":"Eric van de Poele","choices":["Eric van de Poele","Bastian Buus","John Rhodes","Derek Warwick"],"chapterId":"f1-belgique"},{"uid":"gen-f1-belgique-17767","category":"sports","question":"Pilote F1 Belgique ?","answer":"Willy Mairesse","choices":["Gabriele Tarquini","Bill Vukovich","Willy Mairesse","Len Duncan"],"chapterId":"f1-belgique"},{"uid":"gen-f1-belgique-17768","category":"sports","question":"Pilote F1 Belgique ?","answer":"Johnny Claes","choices":["Christian Goethals","Jonathan Williams","Johnny Claes","Fred Wacker"],"chapterId":"f1-belgique"},{"uid":"gen-f1-belgique-17769","category":"sports","question":"Pilote F1 Belgique ?","answer":"Lucien Bianchi","choices":["Andrea De Cesaris","Lucien Bianchi","Tim Mayer","Bayliss Levrett"],"chapterId":"f1-belgique"},{"uid":"gen-f1-belgique-17770","category":"sports","question":"Pilote F1 Belgique ?","answer":"Georges Berger","choices":["Joe Sostilio","Georges Berger","Raymond Mays","Warwick Brown"],"chapterId":"f1-belgique"},{"uid":"gen-f1-belgique-17771","category":"sports","question":"Pilote F1 Belgique ?","answer":"Jacques Swaters","choices":["Jacques Swaters","Patrick Nève","Tony Brooks","Jack Brabham"],"chapterId":"f1-belgique"},{"uid":"gen-f1-belgique-17772","category":"sports","question":"Pilote F1 Belgique ?","answer":"Roger Laurent","choices":["Roger Laurent","John James","Peter Revson","Perry Grimm"],"chapterId":"f1-belgique"},{"uid":"gen-f1-belgique-17773","category":"sports","question":"Pilote F1 Belgique ?","answer":"Philippe Adams","choices":["George Lynch","Walt Hansgen","Philippe Adams","Pedro Diniz"],"chapterId":"f1-belgique"},{"uid":"gen-f1-belgique-17774","category":"sports","question":"Pilote F1 Belgique ?","answer":"André Pilette","choices":["Marcus Ericsson","Cristiano da Matta","André Pilette","Paul Russo"],"chapterId":"f1-belgique"},{"uid":"gen-f1-belgique-17775","category":"sports","question":"Pilote F1 Belgique ?","answer":"Teddy Pilette","choices":["Paul di Resta","Bud Rose","Teddy Pilette","Andrea De Adamich"],"chapterId":"f1-belgique"}]