[{"uid":"gen-jv-sega-23583","category":"divers","question":"Studio développeur de « Sonic Generations ‘Casino Night’ Pinball » ?","answer":"Sega","choices":["Sega","Armature Studio","Step Creative Group","Chess.com"],"chapterId":"jv-sega"},{"uid":"gen-jv-sega-23584","category":"divers","question":"Studio développeur de « Phantasy Star Collection » ?","answer":"Sega","choices":["Skip Ltd.","Sega","Rogue Entertainment","NetDevil"],"chapterId":"jv-sega"},{"uid":"gen-jv-sega-23585","category":"divers","question":"Studio développeur de « Sega Classics Arcade Collection » ?","answer":"Sega","choices":["Alekseï Pajitnov","Sega","Odyssey Interactive","Cooking Mama Limited"],"chapterId":"jv-sega"},{"uid":"gen-jv-sega-23586","category":"divers","question":"Studio développeur de « Game no Kanzume: Otokuyō » ?","answer":"Sega","choices":["Sega","Reflexive Entertainment","Amaze Entertainment","Tencent"],"chapterId":"jv-sega"},{"uid":"gen-jv-sega-23587","category":"divers","question":"Studio développeur de « The House of the Dead 2 & 3 Return » ?","answer":"Sega","choices":["Institut de technologie du Massachusetts","CrackedGhostGames","Sega","Neople"],"chapterId":"jv-sega"},{"uid":"gen-jv-sega-23588","category":"divers","question":"Studio développeur de « Dreamcast Collection » ?","answer":"Sega","choices":["digradi","CD Projekt","Sega","IMC Games"],"chapterId":"jv-sega"},{"uid":"gen-jv-sega-23589","category":"divers","question":"Studio développeur de « Sega Smash Pack » ?","answer":"Sega","choices":["Ludeon Studios","Sega","Urban Games","Pearl Abyss"],"chapterId":"jv-sega"},{"uid":"gen-jv-sega-23590","category":"divers","question":"Studio développeur de « Sega Classics Collection » ?","answer":"Sega","choices":["David Braben","Sega","Springloaded","Q65619023"],"chapterId":"jv-sega"},{"uid":"gen-jv-sega-23591","category":"divers","question":"Studio développeur de « Sega Mega Drive Classics » ?","answer":"Sega","choices":["Sega","Favorite","Riot Games","http://www.wikidata.org/.well-known/genid/7a8fb439664802a0f010b24967a9affe"],"chapterId":"jv-sega"},{"uid":"gen-jv-sega-23592","category":"divers","question":"Studio développeur de « Sonic Compilation » ?","answer":"Sega","choices":["Sega","Sunrise Swiss","Windmill","2K Marin"],"chapterId":"jv-sega"}]