[{"uid":"gen-mont-venezuela-8168","category":"geo","question":"Sommet de 4978 m situé en ?","answer":"Venezuela","choices":["Égypte","Venezuela","Empire russe","Timor oriental"],"chapterId":"mont-venezuela"},{"uid":"gen-mont-venezuela-8169","category":"geo","question":"Sommet de 4940 m situé en ?","answer":"Venezuela","choices":["Birmanie","Slovénie","Venezuela","Afrique du Sud"],"chapterId":"mont-venezuela"},{"uid":"gen-mont-venezuela-8170","category":"geo","question":"Sommet de 4737 m situé en ?","answer":"Venezuela","choices":["Tadjikistan","Japon","Venezuela","Mozambique"],"chapterId":"mont-venezuela"},{"uid":"gen-mont-venezuela-8171","category":"geo","question":"Sommet de 3660 m situé en ?","answer":"Venezuela","choices":["Venezuela","Cameroun","Italie","Liechtenstein"],"chapterId":"mont-venezuela"},{"uid":"gen-mont-venezuela-8172","category":"geo","question":"Sommet de 2832 m situé en ?","answer":"Venezuela","choices":["Éthiopie","Mexique","Union soviétique","Venezuela"],"chapterId":"mont-venezuela"},{"uid":"gen-mont-venezuela-8173","category":"geo","question":"Sommet de 2810 m situé en ?","answer":"Venezuela","choices":["Autriche","Japon","Kenya","Venezuela"],"chapterId":"mont-venezuela"},{"uid":"gen-mont-venezuela-8174","category":"geo","question":"Sommet de 2500 m situé en ?","answer":"Venezuela","choices":["Bosnie-Herzégovine","Colombie","République populaire de Chine","Venezuela"],"chapterId":"mont-venezuela"},{"uid":"gen-mont-venezuela-8175","category":"geo","question":"Sommet de 2500 m situé en ?","answer":"Venezuela","choices":["Salvador","Irak","République populaire de Chine","Venezuela"],"chapterId":"mont-venezuela"},{"uid":"gen-mont-venezuela-8176","category":"geo","question":"Sommet de 2112 m situé en ?","answer":"Venezuela","choices":["Australie","Vietnam","Ouzbékistan","Venezuela"],"chapterId":"mont-venezuela"}]