[{"uid":"gen-oeuvres-michel-ange-buronarroti-11244","category":"arts","question":"Qui a peint/créé « Stigmates de saint François » ?","answer":"Michel-Ange Buronarroti","choices":["Pietro Scalvini","Michel-Ange Buronarroti","Ambrosius Bosschaert","Hans Thoma"],"chapterId":"oeuvres-michel-ange-buronarroti"},{"uid":"gen-oeuvres-michel-ange-buronarroti-11245","category":"arts","question":"Qui a peint/créé « Le Sacrifice de Noé » ?","answer":"Michel-Ange Buronarroti","choices":["Diego Vélasquez","Michel-Ange Buronarroti","Paulus Potter","Tivadar Kosztka Csontváry"],"chapterId":"oeuvres-michel-ange-buronarroti"},{"uid":"gen-oeuvres-michel-ange-buronarroti-11246","category":"arts","question":"Qui a peint/créé « Salmon, Booz et Jobed » ?","answer":"Michel-Ange Buronarroti","choices":["Piero di Cosimo","Michel-Ange Buronarroti","Franciabigio","Giorgio Vasari"],"chapterId":"oeuvres-michel-ange-buronarroti"},{"uid":"gen-oeuvres-michel-ange-buronarroti-11247","category":"arts","question":"Qui a peint/créé « Amminadab » ?","answer":"Michel-Ange Buronarroti","choices":["Giovanni Bellini","Rogier van der Weyden","Michel-Ange Buronarroti","Stefano Maria Legnani"],"chapterId":"oeuvres-michel-ange-buronarroti"},{"uid":"gen-oeuvres-michel-ange-buronarroti-11248","category":"arts","question":"Qui a peint/créé « La Mise au tombeau » ?","answer":"Michel-Ange Buronarroti","choices":["Ercole de’ Roberti","Giovanni Gerolamo Savoldo","Michel-Ange Buronarroti","http://www.wikidata.org/.well-known/genid/6d9e5f199ec92e92e9247dccfcd792e3"],"chapterId":"oeuvres-michel-ange-buronarroti"},{"uid":"gen-oeuvres-michel-ange-buronarroti-11249","category":"arts","question":"Qui a peint/créé « The Holy Family with Saint John the Baptist » ?","answer":"Michel-Ange Buronarroti","choices":["Maître du haut Rhin","Michel-Ange Buronarroti","Jean-Pierre Franque","Louis-Michel van Loo"],"chapterId":"oeuvres-michel-ange-buronarroti"},{"uid":"gen-oeuvres-michel-ange-buronarroti-11250","category":"arts","question":"Qui a peint/créé « La Séparation des terres et des eaux » ?","answer":"Michel-Ange Buronarroti","choices":["Fabrizio Santafede","Michel-Ange Buronarroti","http://www.wikidata.org/.well-known/genid/589fdfdbf2d490c75d88d781e09bd329","Micco Spadaro"],"chapterId":"oeuvres-michel-ange-buronarroti"},{"uid":"gen-oeuvres-michel-ange-buronarroti-11251","category":"arts","question":"Qui a peint/créé « La Séparation de la lumière et des ténèbres » ?","answer":"Michel-Ange Buronarroti","choices":["Iacopo Bellini","Michel-Ange Buronarroti","François-Joseph Heim","Joseph Mallord William Turner"],"chapterId":"oeuvres-michel-ange-buronarroti"},{"uid":"gen-oeuvres-michel-ange-buronarroti-11252","category":"arts","question":"Qui a peint/créé « Le Serpent d'airain » ?","answer":"Michel-Ange Buronarroti","choices":["Michel-Ange Buronarroti","Cesare da Sesto","Jan Wildens","http://www.wikidata.org/.well-known/genid/ef29c2b7b24c9e0b5827ffd6447b271f"],"chapterId":"oeuvres-michel-ange-buronarroti"},{"uid":"gen-oeuvres-michel-ange-buronarroti-11253","category":"arts","question":"Qui a peint/créé « La Sibylle de Cumes » ?","answer":"Michel-Ange Buronarroti","choices":["Carl Spitzweg","Ford Madox Brown","Michel-Ange Buronarroti","Gustave Caillebotte"],"chapterId":"oeuvres-michel-ange-buronarroti"}]