[{"uid":"gen-pays-tanzanie-329","category":"geo","question":"Quelle est la capitale de Tanzanie ?","answer":"Dodoma","choices":["Amsterdam","Dodoma","Buenos Aires","Riyad"],"chapterId":"pays-tanzanie"},{"uid":"gen-pays-tanzanie-330","category":"geo","question":"Langue officielle en Tanzanie ?","answer":"anglais","choices":["kalanga","anglais","bozo","langue des signes sud-africaine"],"chapterId":"pays-tanzanie"},{"uid":"gen-pays-tanzanie-331","category":"geo","question":"Langue officielle en Tanzanie ?","answer":"swahili","choices":["swahili","pachto","zoulou","songhaï"],"chapterId":"pays-tanzanie"},{"uid":"gen-pays-tanzanie-332","category":"geo","question":"Monnaie du Tanzanie ?","answer":"shilling tanzanien","choices":["Dirham des Émirats arabes unis","rand","shilling tanzanien","livre soudanaise"],"chapterId":"pays-tanzanie"},{"uid":"gen-pays-tanzanie-333","category":"geo","question":"Sur quel continent se situe Tanzanie ?","answer":"Afrique","choices":["Asie","Amérique du Sud","Afrique","Océanie"],"chapterId":"pays-tanzanie"}]