[{"uid":"gen-pays-sainte-lucie-279","category":"geo","question":"Quelle est la capitale de Sainte-Lucie ?","answer":"Castries","choices":["Djouba","Castries","Bangui","Athènes"],"chapterId":"pays-sainte-lucie"},{"uid":"gen-pays-sainte-lucie-280","category":"geo","question":"Langue officielle en Sainte-Lucie ?","answer":"anglais","choices":["islandais","anglais","papiamento","langue des signes vénézuélienne"],"chapterId":"pays-sainte-lucie"},{"uid":"gen-pays-sainte-lucie-281","category":"geo","question":"Monnaie du Sainte-Lucie ?","answer":"dollar des Caraïbes orientales","choices":["denar macédonien","dollar des Caraïbes orientales","franc comorien","rial yéménite"],"chapterId":"pays-sainte-lucie"},{"uid":"gen-pays-sainte-lucie-282","category":"geo","question":"Sur quel continent se situe Sainte-Lucie ?","answer":"Amérique du Nord","choices":["Amérique du Nord","Europe","Océanie","Amérique du Sud"],"chapterId":"pays-sainte-lucie"}]