[{"uid":"gen-pays-france-520","category":"geo","question":"Quelle est la capitale de France ?","answer":"Paris","choices":["Vienne","Paris","Asuncion","Quito"],"chapterId":"pays-france"},{"uid":"gen-pays-france-521","category":"geo","question":"Langue officielle en France ?","answer":"français","choices":["fidjien","malgache","français","tsou"],"chapterId":"pays-france"},{"uid":"gen-pays-france-522","category":"geo","question":"Monnaie du France ?","answer":"Euro","choices":["roupie mauricienne","East Timor centavo coins","peso cubain","Euro"],"chapterId":"pays-france"},{"uid":"gen-pays-france-523","category":"geo","question":"Sur quel continent se situe France ?","answer":"Europe","choices":["Afrique","Amérique du Nord","Océanie","Europe"],"chapterId":"pays-france"}]