[{"uid":"gen-pays-lesotho-541","category":"geo","question":"Quelle est la capitale de Lesotho ?","answer":"Maseru","choices":["Maseru","Jérusalem-Est","Addis-Abeba","Conakry"],"chapterId":"pays-lesotho"},{"uid":"gen-pays-lesotho-542","category":"geo","question":"Langue officielle en Lesotho ?","answer":"anglais","choices":["anglais","anglais australien","comorien","afrikaans"],"chapterId":"pays-lesotho"},{"uid":"gen-pays-lesotho-543","category":"geo","question":"Langue officielle en Lesotho ?","answer":"sotho du Sud","choices":["sotho du Sud","langues en Guinée","putonghua","hiri motou"],"chapterId":"pays-lesotho"},{"uid":"gen-pays-lesotho-544","category":"geo","question":"Monnaie du Lesotho ?","answer":"rand","choices":["couronne suédoise","rand","nouveau dollar de Taïwan","riel"],"chapterId":"pays-lesotho"},{"uid":"gen-pays-lesotho-545","category":"geo","question":"Sur quel continent se situe Lesotho ?","answer":"Afrique","choices":["Amérique du Nord","Amérique du Sud","Afrique","Europe"],"chapterId":"pays-lesotho"}]