[{"uid":"gen-pays-liban-325","category":"geo","question":"Quelle est la capitale de Liban ?","answer":"Beyrouth","choices":["Ras el Khaïmah","Port-Vila","Douchanbé","Beyrouth"],"chapterId":"pays-liban"},{"uid":"gen-pays-liban-326","category":"geo","question":"Langue officielle en Liban ?","answer":"arabe","choices":["tétoum","slovaque","ndau","arabe"],"chapterId":"pays-liban"},{"uid":"gen-pays-liban-327","category":"geo","question":"Monnaie du Liban ?","answer":"livre libanaise","choices":["leu moldave","Sum","franc Pacifique","livre libanaise"],"chapterId":"pays-liban"},{"uid":"gen-pays-liban-328","category":"geo","question":"Sur quel continent se situe Liban ?","answer":"Asie","choices":["Océanie","Asie","Europe","Amérique du Nord"],"chapterId":"pays-liban"}]