[{"uid":"gen-pays-colombie-1029","category":"geo","question":"Quelle est la capitale de Colombie ?","answer":"Bogota","choices":["Oranjestad","Khartoum","Athènes","Bogota"],"chapterId":"pays-colombie"},{"uid":"gen-pays-colombie-1030","category":"geo","question":"Langue officielle en Colombie ?","answer":"espagnol","choices":["espagnol","langue des signes taïwanaise","nrebele","dzongkha"],"chapterId":"pays-colombie"},{"uid":"gen-pays-colombie-1031","category":"geo","question":"Monnaie du Colombie ?","answer":"peso colombien","choices":["peso colombien","Quetzal","franc comorien","livre sterling"],"chapterId":"pays-colombie"},{"uid":"gen-pays-colombie-1032","category":"geo","question":"Sur quel continent se situe Colombie ?","answer":"Amérique du Sud","choices":["Amérique du Sud","Afrique","Amérique du Nord","Europe"],"chapterId":"pays-colombie"}]