[{"uid":"gen-poet-r-publique-de-chine-17041","category":"arts","question":"Poète république de Chine ?","answer":"Lu Xun","choices":["Thomas Telford","Lu Xun","Dhani Ram Chatrik","Emil Rittershaus"],"chapterId":"poet-r-publique-de-chine"},{"uid":"gen-poet-r-publique-de-chine-17042","category":"arts","question":"Poète république de Chine ?","answer":"Mao Zedong","choices":["Jacques-Bénigne Bossuet","Jean Baptista von Schweitzer","Mao Zedong","Sebastian Droste"],"chapterId":"poet-r-publique-de-chine"},{"uid":"gen-poet-r-publique-de-chine-17043","category":"arts","question":"Poète république de Chine ?","answer":"Qi Baishi","choices":["Antoine-Ulrich de Brunswick-Wolfenbüttel","Knut Hamsun","Qi Baishi","George William Russell"],"chapterId":"poet-r-publique-de-chine"},{"uid":"gen-poet-r-publique-de-chine-17044","category":"arts","question":"Poète république de Chine ?","answer":"Zheng Manqing","choices":["Zheng Manqing","Haimo L. Handl","Hovhannès Toumanian","Mina Loy"],"chapterId":"poet-r-publique-de-chine"},{"uid":"gen-poet-r-publique-de-chine-17045","category":"arts","question":"Poète république de Chine ?","answer":"Bing Xin","choices":["Evelina Cattermole","Bing Xin","Delmira Agustini","Timothy Dwight"],"chapterId":"poet-r-publique-de-chine"},{"uid":"gen-poet-r-publique-de-chine-17046","category":"arts","question":"Poète république de Chine ?","answer":"Yu Dafu","choices":["Yılmaz Güney","Yu Dafu","George Richmond","Heinrich Harries"],"chapterId":"poet-r-publique-de-chine"}]