[{"uid":"gen-sci-bio-empire-allemand-6070","category":"sciences","question":"Quel biologiste Empire allemand célèbre ?","answer":"Dietrich Starck","choices":["Karl Sigismund Kunth","Theodor Escherich","Karl Bogislaus Reichert","Dietrich Starck"],"chapterId":"sci-bio-empire-allemand"},{"uid":"gen-sci-bio-empire-allemand-6071","category":"sciences","question":"Quel biologiste Empire allemand célèbre ?","answer":"Guillaume Philippe Schimper","choices":["Alain Reinberg","Guillaume Philippe Schimper","Zheng Ji","J.-André Fortin"],"chapterId":"sci-bio-empire-allemand"},{"uid":"gen-sci-bio-empire-allemand-6072","category":"sciences","question":"Quel biologiste Empire allemand célèbre ?","answer":"Oscar Hertwig","choices":["Oscar Hertwig","Josephus Nicolaus Laurenti","C. R. Narayan Rao","Hartmut Wekerle"],"chapterId":"sci-bio-empire-allemand"},{"uid":"gen-sci-bio-empire-allemand-6073","category":"sciences","question":"Quel biologiste Empire allemand célèbre ?","answer":"Richard Wolfgang Semon","choices":["Clodoveo Carrión","Aurora Chirinos Pizarro","Richard Wolfgang Semon","Frederic Vester"],"chapterId":"sci-bio-empire-allemand"},{"uid":"gen-sci-bio-empire-allemand-6074","category":"sciences","question":"Quel biologiste Empire allemand célèbre ?","answer":"Joachim Hämmerling","choices":["Edwin Ellen Goldmann","Roger Kornberg","Joachim Hämmerling","Stanislav Komárek"],"chapterId":"sci-bio-empire-allemand"},{"uid":"gen-sci-bio-empire-allemand-6075","category":"sciences","question":"Quel biologiste Empire allemand célèbre ?","answer":"Oskar Neumann","choices":["Eugenio Ruspoli","Oskar Neumann","Johnjoe Mac Fadden","Andreï Bannikov"],"chapterId":"sci-bio-empire-allemand"},{"uid":"gen-sci-bio-empire-allemand-6076","category":"sciences","question":"Quel biologiste Empire allemand célèbre ?","answer":"August von Wassermann","choices":["Adolf Portmann","August von Wassermann","Margaret Oakley Dayhoff","Hans Spemann"],"chapterId":"sci-bio-empire-allemand"},{"uid":"gen-sci-bio-empire-allemand-6077","category":"sciences","question":"Quel biologiste Empire allemand célèbre ?","answer":"Friedrich Markgraf","choices":["Friedrich Markgraf","Isabelle Olivieri","Karl Emil Lischke","Charles Lucien Bonaparte"],"chapterId":"sci-bio-empire-allemand"},{"uid":"gen-sci-bio-empire-allemand-6078","category":"sciences","question":"Quel biologiste Empire allemand célèbre ?","answer":"Robert Koch","choices":["Robert Koch","Galina A. Peschkova","Constantin Rafinesque","Samuel Bowser"],"chapterId":"sci-bio-empire-allemand"},{"uid":"gen-sci-bio-empire-allemand-6079","category":"sciences","question":"Quel biologiste Empire allemand célèbre ?","answer":"Hans Driesch","choices":["Max Fürbringer","John Arthur Thomson","Hans Driesch","Michael Succow"],"chapterId":"sci-bio-empire-allemand"}]