[{"uid":"gen-sci-phys--lectorat-de-saxe-5097","category":"sciences","question":"Quel physicien·ne électorat de Saxe célèbre ?","answer":"Gottfried Wilhelm Leibniz","choices":["Danielle Fong","Gottfried Wilhelm Leibniz","Johann Deisenhofer","Richard Feynman"],"chapterId":"sci-phys--lectorat-de-saxe"},{"uid":"gen-sci-phys--lectorat-de-saxe-5098","category":"sciences","question":"Quel physicien·ne électorat de Saxe célèbre ?","answer":"Carl Friedrich Hindenburg","choices":["Friedrich Paschen","Peter Armbruster","Carl Friedrich Hindenburg","Jennifer Tour Chayes"],"chapterId":"sci-phys--lectorat-de-saxe"},{"uid":"gen-sci-phys--lectorat-de-saxe-5099","category":"sciences","question":"Quel physicien·ne électorat de Saxe célèbre ?","answer":"Heinrich Wilhelm Brandes","choices":["Horst Weber","Dietrich Haarer","Heinrich Wilhelm Brandes","Josef Schintlmeister"],"chapterId":"sci-phys--lectorat-de-saxe"},{"uid":"gen-sci-phys--lectorat-de-saxe-5100","category":"sciences","question":"Quel physicien·ne électorat de Saxe célèbre ?","answer":"Christian Gottlieb Kratzenstein","choices":["Christian Gottlieb Kratzenstein","Michio Jimbō","Georg Zundel","Hans Christian Ørsted"],"chapterId":"sci-phys--lectorat-de-saxe"},{"uid":"gen-sci-phys--lectorat-de-saxe-5101","category":"sciences","question":"Quel physicien·ne électorat de Saxe célèbre ?","answer":"Ehrenfried Walther von Tschirnhaus","choices":["Ehrenfried Walther von Tschirnhaus","Boris Chirikov","Linus Pauling","Eduard Kaeser"],"chapterId":"sci-phys--lectorat-de-saxe"}]