[{"uid":"gen-sci-phys-empire-allemand-5151","category":"sciences","question":"Quel physicien·ne Empire allemand célèbre ?","answer":"August Karl Krönig","choices":["Daniel Chonghan Hong","August Karl Krönig","Jeffrey Goldstone","Alfred Kastler"],"chapterId":"sci-phys-empire-allemand"},{"uid":"gen-sci-phys-empire-allemand-5152","category":"sciences","question":"Quel physicien·ne Empire allemand célèbre ?","answer":"Oskar Emil Meyer","choices":["Alexander Lippisch","Cees Dekker","Oskar Emil Meyer","Hans-Arwed Weidenmüller"],"chapterId":"sci-phys-empire-allemand"},{"uid":"gen-sci-phys-empire-allemand-5153","category":"sciences","question":"Quel physicien·ne Empire allemand célèbre ?","answer":"Philipp von Jolly","choices":["Heinz Oberhummer","Ehrenfried Walther von Tschirnhaus","Philipp von Jolly","Alastair Cameron"],"chapterId":"sci-phys-empire-allemand"},{"uid":"gen-sci-phys-empire-allemand-5154","category":"sciences","question":"Quel physicien·ne Empire allemand célèbre ?","answer":"Theodor Kaluza","choices":["Theodor Kaluza","Alfred Robb","Francis Collins","Salomon Kalischer"],"chapterId":"sci-phys-empire-allemand"},{"uid":"gen-sci-phys-empire-allemand-5155","category":"sciences","question":"Quel physicien·ne Empire allemand célèbre ?","answer":"Hermann Knoblauch","choices":["Leonard Bairstow","Hermann Knoblauch","Pierre Curie","Léna Soler"],"chapterId":"sci-phys-empire-allemand"},{"uid":"gen-sci-phys-empire-allemand-5156","category":"sciences","question":"Quel physicien·ne Empire allemand célèbre ?","answer":"Wilhelm Röntgen","choices":["William Herschel","Wilhelm Röntgen","Arthur March","Simon Singh"],"chapterId":"sci-phys-empire-allemand"},{"uid":"gen-sci-phys-empire-allemand-5157","category":"sciences","question":"Quel physicien·ne Empire allemand célèbre ?","answer":"David Hilbert","choices":["Jacques Villain","David Hilbert","Alan Boss","A. Brooks Harris"],"chapterId":"sci-phys-empire-allemand"},{"uid":"gen-sci-phys-empire-allemand-5158","category":"sciences","question":"Quel physicien·ne Empire allemand célèbre ?","answer":"Ernst August Friedrich Ruska","choices":["Fritz Bopp","Charles H. Moore","Ernst August Friedrich Ruska","Walther Gerlach"],"chapterId":"sci-phys-empire-allemand"},{"uid":"gen-sci-phys-empire-allemand-5159","category":"sciences","question":"Quel physicien·ne Empire allemand célèbre ?","answer":"Hermann Weyl","choices":["Georg von Neumayer","Tobias Mayer","Hermann Weyl","Subhash Kak"],"chapterId":"sci-phys-empire-allemand"}]