[{"uid":"gen-sci-phys-troisi-me-reich-5102","category":"sciences","question":"Quel physicien·ne Troisième Reich célèbre ?","answer":"Erwin Schrödinger","choices":["Theodor Grotthuss","Erwin Schrödinger","Reimar Lüst","Edward Kolb"],"chapterId":"sci-phys-troisi-me-reich"},{"uid":"gen-sci-phys-troisi-me-reich-5103","category":"sciences","question":"Quel physicien·ne Troisième Reich célèbre ?","answer":"Gerhard Herzberg","choices":["Nicolas Copernic","Gerhard Herzberg","Alexandre Mikhaïlovitch Prokhorov","Hans Suess"],"chapterId":"sci-phys-troisi-me-reich"},{"uid":"gen-sci-phys-troisi-me-reich-5104","category":"sciences","question":"Quel physicien·ne Troisième Reich célèbre ?","answer":"Theodor Kaluza","choices":["Theodore Maiman","Peter Salcher","Theodor Kaluza","Dorit Aharonov"],"chapterId":"sci-phys-troisi-me-reich"},{"uid":"gen-sci-phys-troisi-me-reich-5105","category":"sciences","question":"Quel physicien·ne Troisième Reich célèbre ?","answer":"Helmut Gröttrup","choices":["Wolfhart Zimmermann","Ernst Ising","Helmut Gröttrup","Irene Sänger-Bredt"],"chapterId":"sci-phys-troisi-me-reich"},{"uid":"gen-sci-phys-troisi-me-reich-5106","category":"sciences","question":"Quel physicien·ne Troisième Reich célèbre ?","answer":"David Hilbert","choices":["David Hilbert","Ernst Christian Julius Schering","Heinz London","Jonathan Zenneck"],"chapterId":"sci-phys-troisi-me-reich"},{"uid":"gen-sci-phys-troisi-me-reich-5107","category":"sciences","question":"Quel physicien·ne Troisième Reich célèbre ?","answer":"Ernst August Friedrich Ruska","choices":["Paul Alfred Biefeld","Ernst August Friedrich Ruska","Theodor Erhard","Alexander Weissberg-Cybulski"],"chapterId":"sci-phys-troisi-me-reich"}]