[{"uid":"gen-unesco-mexique-1611","category":"arts","question":"Ce site UNESCO se trouve dans quel pays ? · Chichén Itzá","answer":"Mexique","choices":["Irak","Mexique","Slovaquie","Nicaragua"],"chapterId":"unesco-mexique"},{"uid":"gen-unesco-mexique-1612","category":"arts","question":"Ce site UNESCO se trouve dans quel pays ? · hospice Cabañas","answer":"Mexique","choices":["Zambie","Namibie","Mexique","Mozambique"],"chapterId":"unesco-mexique"},{"uid":"gen-unesco-mexique-1613","category":"arts","question":"Ce site UNESCO se trouve dans quel pays ? · Calakmul","answer":"Mexique","choices":["Rwanda","Belize","Mexique","République populaire de Chine"],"chapterId":"unesco-mexique"},{"uid":"gen-unesco-mexique-1614","category":"arts","question":"Ce site UNESCO se trouve dans quel pays ? · Ciudad Universitaria","answer":"Mexique","choices":["Mexique","République démocratique du Congo","Saint-Christophe-et-Niévès","Israël"],"chapterId":"unesco-mexique"},{"uid":"gen-unesco-mexique-1615","category":"arts","question":"Ce site UNESCO se trouve dans quel pays ? · Teotihuacan","answer":"Mexique","choices":["République démocratique du Congo","Mexique","Colombie","Îles Salomon"],"chapterId":"unesco-mexique"},{"uid":"gen-unesco-mexique-1616","category":"arts","question":"Ce site UNESCO se trouve dans quel pays ? · peintures rupestres de la Sierra de San Francisco","answer":"Mexique","choices":["Qatar","Mexique","Liban","Vietnam"],"chapterId":"unesco-mexique"},{"uid":"gen-unesco-mexique-1617","category":"arts","question":"Ce site UNESCO se trouve dans quel pays ? · Sian Ka'an","answer":"Mexique","choices":["Mexique","Cambodge","Autriche","Madagascar"],"chapterId":"unesco-mexique"},{"uid":"gen-unesco-mexique-1618","category":"arts","question":"Ce site UNESCO se trouve dans quel pays ? · Missions franciscaines de la Sierra Gorda","answer":"Mexique","choices":["Finlande","Ghana","Mexique","Botswana"],"chapterId":"unesco-mexique"},{"uid":"gen-unesco-mexique-1619","category":"arts","question":"Ce site UNESCO se trouve dans quel pays ? · El Tajín","answer":"Mexique","choices":["République démocratique populaire du Yémen","Mongolie","Mexique","Seychelles"],"chapterId":"unesco-mexique"},{"uid":"gen-unesco-mexique-1620","category":"arts","question":"Ce site UNESCO se trouve dans quel pays ? · Xochicalco","answer":"Mexique","choices":["Cuba","Mexique","Irlande","États-Unis"],"chapterId":"unesco-mexique"}]