[{"uid":"gen-unesco-costa-rica-1911","category":"arts","question":"Ce site UNESCO se trouve dans quel pays ? · zone de conservation de Guanacaste","answer":"Costa Rica","choices":["Nicaragua","République du Congo","Costa Rica","Dominique"],"chapterId":"unesco-costa-rica"},{"uid":"gen-unesco-costa-rica-1912","category":"arts","question":"Ce site UNESCO se trouve dans quel pays ? · Établissements de chefferies précolombiennes avec des sphères mégalithiques du Diquís","answer":"Costa Rica","choices":["Costa Rica","Malaisie","Roumanie","Géorgie"],"chapterId":"unesco-costa-rica"},{"uid":"gen-unesco-costa-rica-1913","category":"arts","question":"Ce site UNESCO se trouve dans quel pays ? · parc national de l'île Cocos","answer":"Costa Rica","choices":["Jamaïque","Costa Rica","Tadjikistan","Madagascar"],"chapterId":"unesco-costa-rica"},{"uid":"gen-unesco-costa-rica-1914","category":"arts","question":"Ce site UNESCO se trouve dans quel pays ? · Réserves de la cordillère de Talamanca-La Amistad / Parc national La Amistad","answer":"Costa Rica","choices":["Royaume-Uni","Costa Rica","Haïti","Pakistan"],"chapterId":"unesco-costa-rica"}]