[{"uid":"gen-unesco-liban-1524","category":"arts","question":"Ce site UNESCO se trouve dans quel pays ? · Anjar","answer":"Liban","choices":["Liban","Philippines","Malaisie","Kazakhstan"],"chapterId":"unesco-liban"},{"uid":"gen-unesco-liban-1525","category":"arts","question":"Ce site UNESCO se trouve dans quel pays ? · Byblos","answer":"Liban","choices":["Venezuela","Somalie","Gabon","Liban"],"chapterId":"unesco-liban"},{"uid":"gen-unesco-liban-1526","category":"arts","question":"Ce site UNESCO se trouve dans quel pays ? · Baalbek","answer":"Liban","choices":["Arabie saoudite","République centrafricaine","Philippines","Liban"],"chapterId":"unesco-liban"},{"uid":"gen-unesco-liban-1527","category":"arts","question":"Ce site UNESCO se trouve dans quel pays ? · cathédrale des Croisés de Tyr","answer":"Liban","choices":["Grèce","Papouasie-Nouvelle-Guinée","Burkina Faso","Liban"],"chapterId":"unesco-liban"},{"uid":"gen-unesco-liban-1528","category":"arts","question":"Ce site UNESCO se trouve dans quel pays ? · Foire internationale Rachid Karameh","answer":"Liban","choices":["Fidji","Guinée","Moldavie","Liban"],"chapterId":"unesco-liban"},{"uid":"gen-unesco-liban-1529","category":"arts","question":"Ce site UNESCO se trouve dans quel pays ? · Tyr","answer":"Liban","choices":["Grèce","Géorgie","Guinée","Liban"],"chapterId":"unesco-liban"},{"uid":"gen-unesco-liban-1530","category":"arts","question":"Ce site UNESCO se trouve dans quel pays ? · Ouadi Qadisha (the Holy Valley) and the Forest of the Cedars of God (Horsh Arz el-Rab)","answer":"Liban","choices":["Estonie","Azerbaïdjan","Sierra Leone","Liban"],"chapterId":"unesco-liban"},{"uid":"gen-unesco-liban-1531","category":"arts","question":"Ce site UNESCO se trouve dans quel pays ? · temple de Jupiter","answer":"Liban","choices":["Liban","Ouzbékistan","Union soviétique","Cuba"],"chapterId":"unesco-liban"}]