[{"uid":"gen-unesco-slov-nie-1470","category":"arts","question":"Ce site UNESCO se trouve dans quel pays ? · forêts primaires de hêtres des Carpates et forêts anciennes de hêtres d’Allemagne","answer":"Slovénie","choices":["Slovénie","Afghanistan","Haïti","Cambodge"],"chapterId":"unesco-slov-nie"},{"uid":"gen-unesco-slov-nie-1471","category":"arts","question":"Ce site UNESCO se trouve dans quel pays ? · sites palafittiques préhistoriques autour des Alpes","answer":"Slovénie","choices":["Australie","Irak","Slovénie","Pakistan"],"chapterId":"unesco-slov-nie"},{"uid":"gen-unesco-slov-nie-1472","category":"arts","question":"Ce site UNESCO se trouve dans quel pays ? · grottes de Škocjan","answer":"Slovénie","choices":["Ouganda","Nicaragua","Slovénie","Sultanat Mahri de Qishn et Socotra"],"chapterId":"unesco-slov-nie"},{"uid":"gen-unesco-slov-nie-1473","category":"arts","question":"Ce site UNESCO se trouve dans quel pays ? · Les œuvres de Jože Plečnik à Ljubljana","answer":"Slovénie","choices":["Liban","Slovaquie","Slovénie","Vietnam"],"chapterId":"unesco-slov-nie"},{"uid":"gen-unesco-slov-nie-1474","category":"arts","question":"Ce site UNESCO se trouve dans quel pays ? · patrimoine du mercure","answer":"Slovénie","choices":["Lesotho","Slovénie","Namibie","Danemark"],"chapterId":"unesco-slov-nie"}]