[{"uid":"gen-villes--tats-unis-2218","category":"geo","question":"Dans quel pays se trouve Grand New York ? (19.9M hab.)","answer":"États-Unis","choices":["Togo","États-Unis","Moldavie","Finlande"],"chapterId":"villes--tats-unis"},{"uid":"gen-villes--tats-unis-2219","category":"geo","question":"Dans quel pays se trouve New York ? (8.8M hab.)","answer":"États-Unis","choices":["États-Unis","Moldavie","Thaïlande","Sri Lanka"],"chapterId":"villes--tats-unis"},{"uid":"gen-villes--tats-unis-2220","category":"geo","question":"Dans quel pays se trouve New York ? (8.8M hab.)","answer":"États-Unis","choices":["États-Unis","État de Palestine","Pologne","Guinée"],"chapterId":"villes--tats-unis"},{"uid":"gen-villes--tats-unis-2221","category":"geo","question":"Dans quel pays se trouve New York ? (8.8M hab.)","answer":"États-Unis","choices":["Mexique","Serbie","États-Unis","Mali"],"chapterId":"villes--tats-unis"},{"uid":"gen-villes--tats-unis-2222","category":"geo","question":"Dans quel pays se trouve New York ? (8.8M hab.)","answer":"États-Unis","choices":["Vietnam","Pakistan","États-Unis","Birmanie"],"chapterId":"villes--tats-unis"},{"uid":"gen-villes--tats-unis-2223","category":"geo","question":"Dans quel pays se trouve New York ? (8.8M hab.)","answer":"États-Unis","choices":["Tunisie","États-Unis","Iran","Zimbabwe"],"chapterId":"villes--tats-unis"},{"uid":"gen-villes--tats-unis-2224","category":"geo","question":"Dans quel pays se trouve New York ? (8.8M hab.)","answer":"États-Unis","choices":["États-Unis","Russie","Colombie","Tchad"],"chapterId":"villes--tats-unis"},{"uid":"gen-villes--tats-unis-2225","category":"geo","question":"Dans quel pays se trouve New York ? (8.8M hab.)","answer":"États-Unis","choices":["États-Unis","Mongolie","Belgique","République populaire de Chine"],"chapterId":"villes--tats-unis"},{"uid":"gen-villes--tats-unis-2226","category":"geo","question":"Dans quel pays se trouve New York ? (8.8M hab.)","answer":"États-Unis","choices":["Indonésie","États-Unis","Finlande","Koweït"],"chapterId":"villes--tats-unis"},{"uid":"gen-villes--tats-unis-2227","category":"geo","question":"Dans quel pays se trouve New York ? (8.8M hab.)","answer":"États-Unis","choices":["Cuba","Liban","Indonésie","États-Unis"],"chapterId":"villes--tats-unis"}]